mii/__init__.py
mii/database.py
mii/models.py
mii/parser.py
mii/types.py
mii_cli/__init__.py
mii_lib-0.1.0.dist-info/licenses/LICENSE
mii_lib-0.1.0.dist-info/METADATA
mii_lib-0.1.0.dist-info/WHEEL
mii_lib-0.1.0.dist-info/entry_points.txt
mii_lib-0.1.0.dist-info/top_level.txt
mii_lib-0.1.0.dist-info/RECORD
