Metadata-Version: 2.4
Name: mii-lib
Version: 0.1.0
Summary: Library and CLI tool for extracting and analyzing Mii files from Nintendo console database dumps
Requires-Python: >=3.9
License-File: LICENSE
Provides-Extra: cli
Requires-Dist: typer>=0.17.4; extra == "cli"
Requires-Dist: rich>=13.0.0; extra == "cli"
Provides-Extra: docs
Requires-Dist: mkdocs>=1.5.0; extra == "docs"
Requires-Dist: mkdocs-material>=9.0.0; extra == "docs"
Requires-Dist: mkdocstrings[python]>=0.24.0; extra == "docs"
Dynamic: license-file
